django_loose_fk/__init__.py
django_loose_fk/apps.py
django_loose_fk/checks.py
django_loose_fk/constraints.py
django_loose_fk/drf.py
django_loose_fk/fields.py
django_loose_fk/filters.py
django_loose_fk/loaders.py
django_loose_fk/lookups.py
django_loose_fk/py.typed
django_loose_fk/query_list.py
django_loose_fk/utils.py
django_loose_fk/virtual_models.py
django_loose_fk/oas_extensions/__init__.py
django_loose_fk/oas_extensions/fields.py
django_loose_fk/oas_extensions/query.py
django_loose_fk-1.1.2.dist-info/licenses/LICENSE
testapp/__init__.py
testapp/api.py
testapp/apps.py
testapp/loaders.py
testapp/models.py
testapp/settings.py
testapp/urls.py
testapp/migrations/0001_initial.py
testapp/migrations/0002_auto_20220310_1612.py
testapp/migrations/0003_auto_20230705_0917.py
testapp/migrations/0004_zaakobjectfk.py
testapp/migrations/__init__.py
tests/__init__.py
tests/conftest.py
tests/test_api.py
tests/test_api_docs.py
tests/test_chain_loose_fk.py
tests/test_compare.py
tests/test_filter.py
tests/test_integrity.py
tests/test_is_local.py
tests/test_loaders.py
tests/test_model_field_interface.py
tests/test_model_layer.py
tests/test_querying.py
tests/test_querylist.py
tests/test_serializer_field.py
tests/test_system_checks.py
django_loose_fk-1.1.2.dist-info/METADATA
django_loose_fk-1.1.2.dist-info/WHEEL
django_loose_fk-1.1.2.dist-info/top_level.txt
django_loose_fk-1.1.2.dist-info/RECORD
