Metadata-Version: 2.4
Name: django-loose-fk
Version: 1.1.2
Summary: Django Loose FK handles local or remote "ForeignKey" references.
Home-page: https://github.com/maykinmedia/django-loose-fk
Author: Maykin Media
Author-email: support@maykinmedia.nl
License: MIT
Keywords: ForeignKey,URL reference,decentralization,integrity
Classifier: Development Status :: 5 - Production/Stable
Classifier: Framework :: Django
Classifier: Framework :: Django :: 3.2
Classifier: Framework :: Django :: 4.2
Classifier: Intended Audience :: Developers
Classifier: Operating System :: Unix
Classifier: Operating System :: MacOS
Classifier: Operating System :: Microsoft :: Windows
Classifier: Programming Language :: Python :: 3.10
Classifier: Programming Language :: Python :: 3.11
Classifier: Topic :: Software Development :: Libraries :: Python Modules
License-File: LICENSE
Requires-Dist: django>=3.2
Requires-Dist: djangorestframework>=3.11.0
Requires-Dist: django-filter
Requires-Dist: coreapi
Provides-Extra: openapi
Requires-Dist: drf-spectacular; extra == "openapi"
Provides-Extra: tests
Requires-Dist: psycopg2; extra == "tests"
Requires-Dist: pytest; extra == "tests"
Requires-Dist: pytest-django; extra == "tests"
Requires-Dist: tox; extra == "tests"
Requires-Dist: black; extra == "tests"
Requires-Dist: isort; extra == "tests"
Requires-Dist: requests; extra == "tests"
Requires-Dist: requests-mock; extra == "tests"
Provides-Extra: pep8
Requires-Dist: flake8; extra == "pep8"
Provides-Extra: coverage
Requires-Dist: pytest-cov; extra == "coverage"
Provides-Extra: docs
Requires-Dist: sphinx; extra == "docs"
Requires-Dist: sphinx-rtd-theme; extra == "docs"
Provides-Extra: release
Requires-Dist: bump2version; extra == "release"
Dynamic: license-file
